{
  "url": "http://globalvoicesonline.org/?p=184119",
  "id": "184119",
  "body": "Haumaldives explains how the Gross national Happiness of Maldivians remained stagnant for the past two years since Maldives under went the transition to democracy.",
  "original_body": "<em>Haumaldives</em> <a href=\"http://haumaldives.wordpress.com/2010/12/03/how-gross-national-happiness-of-maldives-stayed-static-at-zero-for-the-past-2-years/\">explains</a> how the Gross national Happiness of Maldivians remained stagnant for the past two years since Maldives under went the transition to democracy.",
  "title": "Maldives: Wither Happiness?",
  "byline": "rezwan",
  "pub_date": "2011-01-02T21:02:17Z",
  "decompositions": {
    "sentence": [
      "Haumaldives explains how the Gross national Happiness of Maldivians remained stagnant for the past two years since Maldives under went the transition to democracy."
    ],
    "tokens": [
      "Haumaldives",
      "explains",
      "how",
      "the",
      "Gross",
      "national",
      "Happiness",
      "of",
      "Maldivians",
      "remained",
      "stagnant",
      "for",
      "the",
      "past",
      "two",
      "years",
      "since",
      "Maldives",
      "under",
      "went",
      "the",
      "transition",
      "to",
      "democracy"
    ]
  }
}