{
  "url": "http://globalvoicesonline.org/?p=187964",
  "id": "187964",
  "body": "\"Préval, who will complete his mandate which runs from 2006 to 2011, has betrayed the aspirations of the Haitian people. Now he organizes the return of a dictator who should be judged for his crimes\": The Haitian Blogger translates a French blog post that opines about the return of Duvalier to Haiti. ",
  "original_body": "\"Préval, who will complete his mandate which runs from 2006 to 2011, has betrayed the aspirations of the Haitian people. Now he organizes the return of a dictator who should be judged for his crimes\": <em><a href=\"http://thehaitianblogger.blogspot.com/2011/01/poor-haiti-after-earthquake-cholera-now.html\">The Haitian Blogger</a></em> translates a French blog post that opines about the return of Duvalier to Haiti. ",
  "title": "Haiti: About \"Baby Doc\" ",
  "byline": "Janine Mendes-Franco",
  "pub_date": "2011-01-19T17:59:22Z"
}