{
  "url": "http://globalvoicesonline.org/?p=191151",
  "id": "191151",
  "body": "Emily L. Hauser writes memories from Cairo as she prays for the Egyptian people: \"I know that the Egyptians don’t love the peace that Sadat signed with us. I know that they hate the occupation, distrust Israel and the US because of it, are prone to believing mildly (and not-so-mildly) anti-Semitic conspiracy theories. I know that the Magen David, the Star of David, the symbol of my faith, is often used by them as a symbol of evil. I know these things. But in my heart, they are my people, too.\"Read more",
  "original_body": "Emily L. Hauser writes memories from Cairo as she prays for the Egyptian people: \"I know that the Egyptians don’t love the peace that Sadat signed with us. I know that they hate the occupation, distrust Israel and the US because of it, are prone to believing mildly (and not-so-mildly) anti-Semitic conspiracy theories. I know that the Magen David, the Star of David, the symbol of my faith, is often used by them as a symbol of evil. I know these things. But in my heart, they are my people, too.\"<a href='http://emilylhauserinmyhead.wordpress.com/2011/01/31/israeli-egypt/' >Read more</a>",
  "title": "Israel: Why this Israeli is so invested in Egypt?",
  "byline": "Carmel L. Vaisman",
  "pub_date": "2011-02-04T22:14:08Z"
}