{
  "url": "http://globalvoicesonline.org/?p=194240",
  "id": "194240",
  "body": "Julia Ioffe, Sean Guillory and Anatoly Karlin write about the expulsion of Guardian's Moscow correspondent Luke Harding from Russia.",
  "original_body": "<a href=\"http://www.foreignpolicy.com/articles/2011/02/07/out_of_country?page=full\">Julia Ioffe</a>, <a href=\"http://seansrussiablog.org/2011/02/08/the-hard-lessons-of-the-harding-affair/\">Sean Guillory</a> and <a href=\"http://www.sublimeoblivion.com/2011/02/08/guardian-censorship-luke-harding-plagiarist/\">Anatoly Karlin</a> write about the expulsion of Guardian's Moscow correspondent <a href=\"http://www.guardian.co.uk/profile/lukeharding\">Luke Harding</a> from Russia.",
  "title": "Russia: Guardian's Luke Harding Expelled From Russia",
  "byline": "Veronica Khokhlova",
  "pub_date": "2011-02-09T03:10:13Z",
  "decompositions": {
    "sentence": [
      "Julia Ioffe, Sean Guillory and Anatoly Karlin write about the expulsion of Guardian's Moscow correspondent Luke Harding from Russia."
    ],
    "tokens": [
      "Julia",
      "Ioffe",
      ",",
      "Sean",
      "Guillory",
      "and",
      "Anatoly",
      "Karlin",
      "write",
      "about",
      "the",
      "expulsion",
      "of",
      "Guardian",
      "'s",
      "Moscow",
      "correspondent",
      "Luke",
      "Harding",
      "from",
      "Russia"
    ]
  }
}