{
  "url": "http://globalvoicesonline.org/?p=196630",
  "id": "196630",
  "body": "Ginger of ManilaReviews writes about the 16th Philippine International Hot Air Balloon Fiesta in Clark, Pampanga.\n",
  "original_body": "Ginger of <em>ManilaReviews</em> writes about the 16th Philippine International <a href=\"http://manilareviews.com/2011/02/16th-philippine-international-hot-air-balloon-fiesta-clark-hotels.html\">Hot Air Balloon Fiesta</a> in Clark, Pampanga.\n\n",
  "title": "Philippines: Hot air balloon fiesta",
  "byline": "mong",
  "pub_date": "2011-02-15T22:46:13Z"
}