{
  "url": "http://globalvoicesonline.org/?p=197430",
  "id": "197430",
  "body": "Not much in the way of strange noises given...\nBut strang headlines on XX, yes. People's yesterday ran...:\nhttp://www.tianya.cn/publicforum/content/develop/1/561734.shtml\n『经济论坛』 [热点资讯]人民日报：理性看待当前的社会公正问题(转载)\n作者：油菜花小姐  发表日期：2011-2-17 10:29:00\n\nWhile comments have since been closed, here is what was there Thursday evening:\n\n【人民日报：理性看待当前的社会公正问题】人民日报今日头版发表署名任理轩的文章称，社会公正是历史的、相对的、具体的，我国正处于并将长期处于社会主义初级阶段，不能脱离现实发展水平去盲目追求社会公正，目前体制机制不健全引起的社会不公在经济社会转型期难以完全避免。\n\n作者：油菜花小姐　回复日期：2011-02-17　10:30:50　\n \n　　人民日报这论调……\n　　“难以完全避免”…………\n　　好吧…………\n\n作者：魔鬼兄弟　回复日期：2011-02-17　10:46:39　\n \n　　这个我到认同，但你能认同他的无作为，他是圣人吗，我们都是猪嘛，没有思想，没有权力，没有发言权，我们只要安静就好，只要不饿死就好，比起在老毛的时候我是多么的幸福，我感谢你们这些所谓的圣人们，，，，，\n\n作者：合子搞咯　回复日期：2011-02-17　10:47:50　\n \n　　唉 唯剩下一声叹息啊\n\n作者：ZPF碧海蓝天　回复日期：2011-02-17　10:52:39　\n \n　　我国正处于并将长期处于社会不公之中\n\n作者：听雨三年　回复日期：2011-02-17　10:53:52　\n \n　　宣传部不肯让统计部专美于前啊\n\n作者：外交委员会　回复日期：2011-02-17　10:53:53　\n \n　　　　败笔，说的未必是全没道理，但在政治上很幼稚\n\n作者：透视123　回复日期：2011-02-17　10:56:35　\n \n　　公正是现制度的最大敌人.\n　　\n　　要公正,必要提改革制度.\n\n作者：幼稚成魔　回复日期：2011-02-17　11:00:18　\n \n　　社会公正是历史的、相对的、具体的，我国正处于并将长期处于社会主义初级阶段，不能脱离现实发展水平去盲目追求社会公正，目前体制机制不健全引起的社会不公在经济社会转型期难以完全避免。\n　　===========================================================\n　　我宣布：我朝的政府信用正式破产！\n\n作者：幼稚成魔　回复日期：2011-02-17　11:02:27　\n \n　　现在是对自由、民主、公正进行限制解释和修正；下一步就会赤裸裸的对真善美进行限制解释和修正。\n\n作者：陈双贝　回复日期：2011-02-17　11:04:36　\n \n　　哈哈哈哈\n　　大笑三声\n\n作者：hxsh54321　回复日期：2011-02-17　11:13:10　\n \n　　无耻\n\n作者：小鱼晴　回复日期：2011-02-17　11:14:37　\n \n　　做了鬼就会迷人.经典\n\n作者：油菜花小姐　回复日期：2011-02-17　11:25:56　\n \n　　我们每天都在说正在处于并将长期处于社会主义初级阶段，这个阶段什么时候是个头？\n　　是不是只要有社会不公，只要老百姓质疑社会分配，质疑政策SB，质疑权利腐败，就要拿“初级阶段”出来说事儿？\n　　因为初级阶段，所以什么都是合理的？不是天天吹GDP全球第二了吗？不是天天宣扬人民生活幸福指数提高吗？到底我们什么时候才算走出“初级阶段”呢？\n　　初级阶段的含义就是不管有多不公平，不管有多艰辛和压力大，不管有多看不惯忍不了，都要忍着，一言不发的任人宰割，这就是“初级阶段”了？\n\n作者：我的落落年华2010　回复日期：2011-02-17　11:58:59　\n \n　　初级阶段真是万能的挡箭牌呀\n\n作者：苦骥　回复日期：2011-02-17　15:51:08　\n \n　　唉，它们能否像正常的人类一样思维一次？\n\n作者：透视123　回复日期：2011-02-17　16:20:27　\n \n　　证明不公平有合理性,继续不公平.\n\n作者：又封了一个　回复日期：2011-02-17　16:26:14　\n \n　　不追求公正的社会一定灭亡！我认为这篇社论是认罪书，也是催命符。\n\n作者：chenyf791015　回复日期：2011-02-17　16:36:52　\n \n　　承认现在社会不公正就好！\n\n作者：找不到的那些花儿　回复日期：2011-02-17　19:38:02　\n \n　　我不理解的是，这样的论调都已经公开发表了哦，写这稿子的人是吃什么长大的，将来好意思下去见自己爹娘吗？\n\n作者：都是忽悠　回复日期：2011-02-17　19:41:23　\n \n　　作者：找不到的那些花儿　回复日期：2011-02-17　19:38:02　 \n　　\n　　　　我不理解的是，这样的论调都已经公开发表了哦，写这稿子的人是吃什么长大的，将来好意思下去见自己爹娘吗？\n　　\n　　 \n　　-------------放心这不是个人写的，这是组织上的精神，没见作者名字么\n\n作者：dpca2008　回复日期：2011-02-17　19:49:30　\n \n　　谁掌握了话语权\n　　谁就是理性的\n　　\n　　谁敢反对\n　　谁就是不理性的\n　　\n　　哈哈哈\n\n作者：ct01019　回复日期：2011-02-17　19:56:53　\n \n　　开始新一轮的洗脑\n",
  "original_body": "Not much in the way of strange noises given...\nBut strang headlines on XX, yes. People's yesterday ran...:\nhttp://www.tianya.cn/publicforum/content/develop/1/561734.shtml\n『经济论坛』 [热点资讯]人民日报：理性看待当前的社会公正问题(转载)\n作者：油菜花小姐  发表日期：2011-2-17 10:29:00\n\nWhile comments have since been closed, here is what was there Thursday evening:\n\n【人民日报：理性看待当前的社会公正问题】人民日报今日头版发表署名任理轩的文章称，社会公正是历史的、相对的、具体的，我国正处于并将长期处于社会主义初级阶段，不能脱离现实发展水平去盲目追求社会公正，目前体制机制不健全引起的社会不公在经济社会转型期难以完全避免。\n\n作者：油菜花小姐　回复日期：2011-02-17　10:30:50　\n \n　　人民日报这论调……\n　　“难以完全避免”…………\n　　好吧…………\n\n作者：魔鬼兄弟　回复日期：2011-02-17　10:46:39　\n \n　　这个我到认同，但你能认同他的无作为，他是圣人吗，我们都是猪嘛，没有思想，没有权力，没有发言权，我们只要安静就好，只要不饿死就好，比起在老毛的时候我是多么的幸福，我感谢你们这些所谓的圣人们，，，，，\n\n作者：合子搞咯　回复日期：2011-02-17　10:47:50　\n \n　　唉 唯剩下一声叹息啊\n\n作者：ZPF碧海蓝天　回复日期：2011-02-17　10:52:39　\n \n　　我国正处于并将长期处于社会不公之中\n\n作者：听雨三年　回复日期：2011-02-17　10:53:52　\n \n　　宣传部不肯让统计部专美于前啊\n\n作者：外交委员会　回复日期：2011-02-17　10:53:53　\n \n　　　　败笔，说的未必是全没道理，但在政治上很幼稚\n\n作者：透视123　回复日期：2011-02-17　10:56:35　\n \n　　公正是现制度的最大敌人.\n　　\n　　要公正,必要提改革制度.\n\n作者：幼稚成魔　回复日期：2011-02-17　11:00:18　\n \n　　社会公正是历史的、相对的、具体的，我国正处于并将长期处于社会主义初级阶段，不能脱离现实发展水平去盲目追求社会公正，目前体制机制不健全引起的社会不公在经济社会转型期难以完全避免。\n　　===========================================================\n　　我宣布：我朝的政府信用正式破产！\n\n作者：幼稚成魔　回复日期：2011-02-17　11:02:27　\n \n　　现在是对自由、民主、公正进行限制解释和修正；下一步就会赤裸裸的对真善美进行限制解释和修正。\n\n作者：陈双贝　回复日期：2011-02-17　11:04:36　\n \n　　哈哈哈哈\n　　大笑三声\n\n作者：hxsh54321　回复日期：2011-02-17　11:13:10　\n \n　　无耻\n\n作者：小鱼晴　回复日期：2011-02-17　11:14:37　\n \n　　做了鬼就会迷人.经典\n\n作者：油菜花小姐　回复日期：2011-02-17　11:25:56　\n \n　　我们每天都在说正在处于并将长期处于社会主义初级阶段，这个阶段什么时候是个头？\n　　是不是只要有社会不公，只要老百姓质疑社会分配，质疑政策SB，质疑权利腐败，就要拿“初级阶段”出来说事儿？\n　　因为初级阶段，所以什么都是合理的？不是天天吹GDP全球第二了吗？不是天天宣扬人民生活幸福指数提高吗？到底我们什么时候才算走出“初级阶段”呢？\n　　初级阶段的含义就是不管有多不公平，不管有多艰辛和压力大，不管有多看不惯忍不了，都要忍着，一言不发的任人宰割，这就是“初级阶段”了？\n\n作者：我的落落年华2010　回复日期：2011-02-17　11:58:59　\n \n　　初级阶段真是万能的挡箭牌呀\n\n作者：苦骥　回复日期：2011-02-17　15:51:08　\n \n　　唉，它们能否像正常的人类一样思维一次？\n\n作者：透视123　回复日期：2011-02-17　16:20:27　\n \n　　证明不公平有合理性,继续不公平.\n\n作者：又封了一个　回复日期：2011-02-17　16:26:14　\n \n　　不追求公正的社会一定灭亡！我认为这篇社论是认罪书，也是催命符。\n\n作者：chenyf791015　回复日期：2011-02-17　16:36:52　\n \n　　承认现在社会不公正就好！\n\n作者：找不到的那些花儿　回复日期：2011-02-17　19:38:02　\n \n　　我不理解的是，这样的论调都已经公开发表了哦，写这稿子的人是吃什么长大的，将来好意思下去见自己爹娘吗？\n\n作者：都是忽悠　回复日期：2011-02-17　19:41:23　\n \n　　作者：找不到的那些花儿　回复日期：2011-02-17　19:38:02　 \n　　\n　　　　我不理解的是，这样的论调都已经公开发表了哦，写这稿子的人是吃什么长大的，将来好意思下去见自己爹娘吗？\n　　\n　　 \n　　-------------放心这不是个人写的，这是组织上的精神，没见作者名字么\n\n作者：dpca2008　回复日期：2011-02-17　19:49:30　\n \n　　谁掌握了话语权\n　　谁就是理性的\n　　\n　　谁敢反对\n　　谁就是不理性的\n　　\n　　哈哈哈\n\n作者：ct01019　回复日期：2011-02-17　19:56:53　\n \n　　开始新一轮的洗脑\n\n",
  "title": null,
  "byline": "Feng37",
  "pub_date": "-1-11-30T00:00:00Z",
  "decompositions": {
    "sentence": [
      "Not much in the way of strange noises given...",
      "But strang headlines on XX, yes.",
      "People's yesterday ran...:\nhttp://www.tianya.cn/publicforum/content/develop/1/561734.shtml",
      "『经济论坛』 [热点资讯]人民日报：理性看待当前的社会公正问题(转载)\n作者：油菜花小姐  发表日期：2011-2-17 10:29:00\n\nWhile comments have since been closed, here is what was there Thursday evening:\n\n【人民日报：理性看待当前的社会公正问题】人民日报今日头版发表署名任理轩的文章称，社会公正是历史的、相对的、具体的，我国正处于并将长期处于社会主义初级阶段，不能脱离现实发展水平去盲目追求社会公正，目前体制机制不健全引起的社会不公在经济社会转型期难以完全避免。\n\n作者：油菜花小姐　回复日期：2011-02-17　10:30:50　\n \n　　人民日报这论调……\n　　“难以完全避免”…………\n　　好吧…………\n\n作者：魔鬼兄弟　回复日期：2011-02-17　10:46:39　\n \n　　这个我到认同，但你能认同他的无作为，他是圣人吗，我们都是猪嘛，没有思想，没有权力，没有发言权，我们只要安静就好，只要不饿死就好，比起在老毛的时候我是多么的幸福，我感谢你们这些所谓的圣人们，，，，，\n\n作者：合子搞咯　回复日期：2011-02-17　10:47:50　\n \n　　唉 唯剩下一声叹息啊\n\n作者：ZPF碧海蓝天　回复日期：2011-02-17　10:52:39　\n \n　　我国正处于并将长期处于社会不公之中\n\n作者：听雨三年　回复日期：2011-02-17　10:53:52　\n \n　　宣传部不肯让统计部专美于前啊\n\n作者：外交委员会　回复日期：2011-02-17　10:53:53　\n \n　　　　败笔，说的未必是全没道理，但在政治上很幼稚\n\n作者：透视123　回复日期：2011-02-17　10:56:35　\n \n　　公正是现制度的最大敌人.",
      "要公正,必要提改革制度.",
      "作者：幼稚成魔　回复日期：2011-02-17　11:00:18　\n \n　　社会公正是历史的、相对的、具体的，我国正处于并将长期处于社会主义初级阶段，不能脱离现实发展水平去盲目追求社会公正，目前体制机制不健全引起的社会不公在经济社会转型期难以完全避免。\n　　===========================================================\n　　我宣布：我朝的政府信用正式破产！\n\n作者：幼稚成魔　回复日期：2011-02-17　11:02:27　\n \n　　现在是对自由、民主、公正进行限制解释和修正；下一步就会赤裸裸的对真善美进行限制解释和修正。\n\n作者：陈双贝　回复日期：2011-02-17　11:04:36　\n \n　　哈哈哈哈\n　　大笑三声\n\n作者：hxsh54321　回复日期：2011-02-17　11:13:10　\n \n　　无耻\n\n作者：小鱼晴　回复日期：2011-02-17　11:14:37　\n \n　　做了鬼就会迷人.经典",
      "作者：油菜花小姐　回复日期：2011-02-17　11:25:56　\n \n　　我们每天都在说正在处于并将长期处于社会主义初级阶段，这个阶段什么时候是个头？\n　　是不是只要有社会不公，只要老百姓质疑社会分配，质疑政策SB，质疑权利腐败，就要拿“初级阶段”出来说事儿？\n　　因为初级阶段，所以什么都是合理的？不是天天吹GDP全球第二了吗？不是天天宣扬人民生活幸福指数提高吗？到底我们什么时候才算走出“初级阶段”呢？\n　　初级阶段的含义就是不管有多不公平，不管有多艰辛和压力大，不管有多看不惯忍不了，都要忍着，一言不发的任人宰割，这就是“初级阶段”了？\n\n作者：我的落落年华2010　回复日期：2011-02-17　11:58:59　\n \n　　初级阶段真是万能的挡箭牌呀\n\n作者：苦骥　回复日期：2011-02-17　15:51:08　\n \n　　唉，它们能否像正常的人类一样思维一次？\n\n作者：透视123　回复日期：2011-02-17　16:20:27　\n \n　　证明不公平有合理性,继续不公平.",
      "作者：又封了一个　回复日期：2011-02-17　16:26:14　\n \n　　不追求公正的社会一定灭亡！我认为这篇社论是认罪书，也是催命符。\n\n作者：chenyf791015　回复日期：2011-02-17　16:36:52　\n \n　　承认现在社会不公正就好！\n\n作者：找不到的那些花儿　回复日期：2011-02-17　19:38:02　\n \n　　我不理解的是，这样的论调都已经公开发表了哦，写这稿子的人是吃什么长大的，将来好意思下去见自己爹娘吗？\n\n作者：都是忽悠　回复日期：2011-02-17　19:41:23　\n \n　　作者：找不到的那些花儿　回复日期：2011-02-17　19:38:02　 \n　　\n　　　　我不理解的是，这样的论调都已经公开发表了哦，写这稿子的人是吃什么长大的，将来好意思下去见自己爹娘吗？\n　　\n　　 \n　　-------------放心这不是个人写的，这是组织上的精神，没见作者名字么\n\n作者：dpca2008　回复日期：2011-02-17　19:49:30　\n \n　　谁掌握了话语权\n　　谁就是理性的\n　　\n　　谁敢反对\n　　谁就是不理性的\n　　\n　　哈哈哈\n\n作者：ct01019　回复日期：2011-02-17　19:56:53　\n \n　　开始新一轮的洗脑\n"
    ],
    "tokens": [
      "Not",
      "much",
      "in",
      "the",
      "way",
      "of",
      "strange",
      "noises",
      "given",
      "But",
      "strang",
      "headlines",
      "on",
      "XX",
      ",",
      "yes",
      "People",
      "'s",
      "yesterday",
      "ran...",
      ":",
      "http",
      "://www.tianya.cn/publicforum/content/develop/1/561734.shtml",
      "『经济论坛",
      "』",
      "[热点资讯",
      "]人民日报：理性看待当前的社会公正问题(",
      "转载",
      ")",
      "作者：油菜花小姐",
      "发表日期：2011-2-17",
      "10:29:00",
      "While",
      "comments",
      "have",
      "since",
      "been",
      "closed",
      ",",
      "here",
      "is",
      "what",
      "was",
      "there",
      "Thursday",
      "evening",
      ":",
      "【人民日报：理性看待当前的社会公正问题】人民日报今日头版发表署名任理轩的文章称，社会公正是历史的、相对的、具体的，我国正处于并将长期处于社会主义初级阶段，不能脱离现实发展水平去盲目追求社会公正，目前体制机制不健全引起的社会不公在经济社会转型期难以完全避免",
      "。",
      "作者：油菜花小姐",
      "回复日期：2011-02-17",
      "10:30:50",
      "人民日报这论调…",
      "…",
      "“难以完全避免”…",
      "…",
      "…",
      "…",
      "好吧……",
      "…",
      "…",
      "作者：魔鬼兄弟",
      "回复日期：2011-02-17",
      "10:46:39",
      "这个我到认同，但你能认同他的无作为，他是圣人吗，我们都是猪嘛，没有思想，没有权力，没有发言权，我们只要安静就好，只要不饿死就好，比起在老毛的时候我是多么的幸福，我感谢你们这些所谓的圣人们，，",
      "，",
      "，",
      "，",
      "作者：合子搞咯",
      "回复日期：2011-02-17",
      "10:47",
      ":50",
      "唉",
      "唯剩下一声叹息啊",
      "作者：ZPF碧海蓝天",
      "回复日期：2011-02-17",
      "10:52:39",
      "我国正处于并将长期处于社会不公之中",
      "作者：听雨三年",
      "回复日期：2011-02-17",
      "10:53",
      ":52",
      "宣传部不肯让统计部专美于前啊",
      "作者：外交委员会",
      "回复日期：2011-02-17",
      "10:53",
      ":53",
      "败笔，说的未必是全没道理，但在政治上很幼稚",
      "作者：透视123",
      "回复日期：2011-02-17",
      "10:56:35",
      "公正是现制度的最大敌人",
      "要公正",
      ",必要提改革制度",
      "作者：幼稚成魔",
      "回复日期：2011-02-17",
      "11:00:18",
      "社会公正是历史的、相对的、具体的，我国正处于并将长期处于社会主义初级阶段，不能脱离现实发展水平去盲目追求社会公正，目前体制机制不健全引起的社会不公在经济社会转型期难以完全避免",
      "。",
      "==",
      "=",
      "=",
      "=",
      "=",
      "=",
      "=",
      "=",
      "=",
      "=",
      "=",
      "=",
      "=",
      "=",
      "=",
      "=",
      "=",
      "=",
      "=",
      "=",
      "=",
      "=",
      "=",
      "=",
      "=",
      "=",
      "=",
      "=",
      "=",
      "=",
      "=",
      "=",
      "=",
      "=",
      "=",
      "=",
      "=",
      "=",
      "=",
      "=",
      "=",
      "=",
      "=",
      "=",
      "=",
      "=",
      "=",
      "=",
      "=",
      "=",
      "=",
      "=",
      "=",
      "=",
      "=",
      "=",
      "=",
      "=",
      "我宣布：我朝的政府信用正式破产",
      "！",
      "作者：幼稚成魔",
      "回复日期：2011-02-17",
      "11:02:27",
      "现在是对自由、民主、公正进行限制解释和修正；下一步就会赤裸裸的对真善美进行限制解释和修正",
      "。",
      "作者：陈双贝",
      "回复日期：2011-02-17",
      "11:04:36",
      "哈哈哈哈",
      "大笑三声",
      "作者：hxsh54321",
      "回复日期：2011-02-17",
      "11:13",
      ":10",
      "无耻",
      "作者：小鱼晴",
      "回复日期：2011-02-17",
      "11:14:37",
      "做了鬼就会迷人",
      "作者：油菜花小姐",
      "回复日期：2011-02-17",
      "11:25",
      ":56",
      "我们每天都在说正在处于并将长期处于社会主义初级阶段，这个阶段什么时候是个头",
      "？",
      "是不是只要有社会不公，只要老百姓质疑社会分配，质疑政策SB，质疑权利腐败，就要拿“初级阶段”出来说事儿",
      "？",
      "因为初级阶段，所以什么都是合理的？不是天天吹GDP全球第二了吗？不是天天宣扬人民生活幸福指数提高吗？到底我们什么时候才算走出“初级阶段”呢",
      "？",
      "初级阶段的含义就是不管有多不公平，不管有多艰辛和压力大，不管有多看不惯忍不了，都要忍着，一言不发的任人宰割，这就是“初级阶段”了",
      "？",
      "作者：我的落落年华2010",
      "回复日期：2011-02-17",
      "11:58:59",
      "初级阶段真是万能的挡箭牌呀",
      "作者：苦骥",
      "回复日期：2011-02-17",
      "15",
      ":51:08",
      "唉，它们能否像正常的人类一样思维一次",
      "？",
      "作者：透视123",
      "回复日期：2011-02-17",
      "16",
      ":20:27",
      "证明不公平有合理性",
      ",继续不公平",
      "作者：又封了一个",
      "回复日期：2011-02-17",
      "16",
      ":26",
      ":14",
      "不追求公正的社会一定灭亡！我认为这篇社论是认罪书，也是催命符",
      "。",
      "作者：chenyf791015",
      "回复日期：2011-02-17",
      "16:36",
      ":52",
      "承认现在社会不公正就好",
      "！",
      "作者：找不到的那些花儿",
      "回复日期：2011-02-17",
      "19:38:02",
      "我不理解的是，这样的论调都已经公开发表了哦，写这稿子的人是吃什么长大的，将来好意思下去见自己爹娘吗",
      "？",
      "作者：都是忽悠",
      "回复日期：2011-02-17",
      "19:41:23",
      "作者：找不到的那些花儿",
      "回复日期：2011-02-17",
      "19:38:02",
      "我不理解的是，这样的论调都已经公开发表了哦，写这稿子的人是吃什么长大的，将来好意思下去见自己爹娘吗",
      "？",
      "-------------放心这不是个人写的，这是组织上的精神，没见作者名字么",
      "作者：dpca2008",
      "回复日期：2011-02-17",
      "19:49:30",
      "谁掌握了话语权",
      "谁就是理性的",
      "谁敢反对",
      "谁就是不理性的",
      "哈哈哈",
      "作者：ct01019",
      "回复日期：2011-02-17",
      "19:56",
      ":53"
    ]
  }
}